src/__init__.py
src/api/__init__.py
src/auth/__init__.py
src/core/__init__.py
src/crud/__init__.py
src/db/__init__.py
src/db_schemas/__init__.py
src/enums/__init__.py
src/main.py
src/response_models/__init__.py
porter_ui-0.0.1.dist-info/LICENSE
porter_ui-0.0.1.dist-info/METADATA
porter_ui-0.0.1.dist-info/WHEEL
porter_ui-0.0.1.dist-info/RECORD
