Metadata-Version: 2.3
Name: porter-ui
Version: 0.0.1
Summary: 
Author: ekharshavardhan851@gmail.com
Requires-Python: >=3.13,<4.0.0
Classifier: Programming Language :: Python :: 3
Classifier: Programming Language :: Python :: 3.13
Requires-Dist: duckdb (>=1.4.3,<2.0.0)
Requires-Dist: fastapi (>=0.128.0,<0.129.0)
Requires-Dist: jinja2 (>=3.1.6,<4.0.0)
Requires-Dist: jinjasql (>=0.1.8,<0.2.0)
Requires-Dist: pydantic (>=2.12.5,<3.0.0)
Requires-Dist: pydantic-settings (>=2.12.0,<3.0.0)
Requires-Dist: requests (>=2.32.5,<3.0.0)
Requires-Dist: typer (>=0.21.0,<0.22.0)
Project-URL: Documentation, https://porter-ui.readthedocs.io/en/latest/
Project-URL: Homepage, https://github.com/sh-harshavardhan/porter-ui.git
